CHANGES.txt
COPYRIGHT.txt
LICENSE.txt
README.txt
TODO.txt
ez_setup.py
setup.cfg
setup.py
docs/Makefile
docs/conf.py
docs/index.rst
docs/.static/logo_hi.gif
docs/.static/repoze.css
repoze/__init__.py
repoze.bfg.xmlrpc.egg-info/PKG-INFO
repoze.bfg.xmlrpc.egg-info/SOURCES.txt
repoze.bfg.xmlrpc.egg-info/dependency_links.txt
repoze.bfg.xmlrpc.egg-info/namespace_packages.txt
repoze.bfg.xmlrpc.egg-info/not-zip-safe
repoze.bfg.xmlrpc.egg-info/requires.txt
repoze.bfg.xmlrpc.egg-info/top_level.txt
repoze/bfg/__init__.py
repoze/bfg/xmlrpc/__init__.py
repoze/bfg/xmlrpc/tests.py